design.sv


module Lift8(clk, reset, req_floor, idle, door, Up, Down, current_floor, requests, max_request, min_request, emergency_stop);

  input clk, reset, emergency_stop;
  input logic [2:0] req_floor;      // 3-bit input for 8 floors (0 to 7)
  output logic [1:0] door;
  output logic [2:0] max_request;
  output logic [2:0] min_request;
  output logic [1:0] Up;
  output logic [1:0] Down;
  output logic [1:0] idle;
  output logic [2:0] current_floor;
  output logic [7:0] requests;

  logic door_timer;
  logic emergency_stopped;
  logic flag=0;

  // Update requests when a new floor is requested
  always @(req_floor)
  begin
    requests[req_floor] = 1;
  // Update max_request and min_request based on requested floors
    if (max_request < req_floor)
    begin
      max_request = req_floor;
    end
    
    if (min_request > req_floor)
    begin
      min_request = req_floor;
    end
    
      // Update max_request and min_request based on current floor
    
    if (requests[max_request] == 0 && req_floor > current_floor)
    begin
      max_request = req_floor;
    end
    
    if (requests[min_request] == 0 && req_floor < current_floor)
    begin
      min_request = req_floor;
    end
    
  end

  // Check and update lift behavior based on current floor
  always @(current_floor )
  begin
    if (requests[current_floor] == 1)
    begin
      idle = 1;
      door = 1;
      requests[current_floor] = 0;
      door_timer = 1; // Start the door timer when opening
    end
  end

  // State machine for lift control
  always @(posedge clk )

  begin     
    if (door_timer == 1)
    begin
      door <= 0; // Close the door after the one clock expires
      //$display("%h", current_floor);
    end
    if (reset)
    begin
      // Reset lift to initial state
      flag=0;
      current_floor <= 0;
      idle <= 0;
      door <= 0; // door open
      Up <= 1;   // going up
      Down <= 0; // not going down
      max_request <= 0;
      min_request <= 7;
      requests <= 0;
      emergency_stopped <= 0; // Initialize emergency stop state
    end
    else if (requests == 0 && !reset)
    begin
      // Stay on the current floor if no requests
      current_floor <= current_floor;
      emergency_stopped <= 0; // Clear emergency stop when not moving
    end
    // emergency
    else if (emergency_stop)
    begin
      // Emergency stop button is turned on
      idle <= 1;
      flag <=1;
      emergency_stopped <= 1; // Set emergency stop state
    end
    else if (emergency_stopped && emergency_stop)
    begin
      // Remain stopped until the emergency stop button is reset
      current_floor <= current_floor;
      door <= 0; // Keep the door closed during an emergency stop
    end
    // emergency reset
    else if (!emergency_stop && flag)
    begin
      // Emergency stop button is turned off
      emergency_stopped <= 0; // Set emergency stop state
      flag <=0;
    end
    else
    begin
      // Normal operation when not in emergency stop
      if (max_request <= 7)
      begin
        if (min_request < current_floor && Down == 1)
        begin
          // Move down one floor
          current_floor <= current_floor - 1;
          door <= 0;
          idle <= 0;
        end
        else if (max_request > current_floor && Up == 1)
        begin
          // Move up one floor
          current_floor <= current_floor + 1;
          door <= 0;
          idle <= 0;
        end
        else if (req_floor == current_floor)
        begin
             // Open door and handle request
            door <= 1;
            idle <= 1;
        end
        else if (max_request == current_floor)
        begin
          Up <= 0;
          Down <= 1;
        end
        else if (min_request == current_floor)
        begin
          Up <= 1;
          Down <= 0;
        end
      end
    end
  end
endmodule

testbench.sv
// Code your testbench here
// or browse Examples
module Lift8_Tb();
  logic clk, reset;
  logic [2:0] req_floor;
  logic [1:0] idle, door, Up, Down;
  logic [2:0] current_floor;
  logic [2:0] max_request, min_request;
  logic [7:0] requests;
  logic emergency_stop;

  Lift8 dut(
    .clk(clk),
    .reset(reset),
    .req_floor(req_floor),
    .idle(idle),
    .door(door),
    .Up(Up),
    .Down(Down),
    .current_floor(current_floor),
    .max_request(max_request),
    .min_request(min_request),
    .requests(requests),
    .emergency_stop(emergency_stop)
  );

  initial begin
    $dumpfile("waveform.vcd"); // Specify the VCD waveform output file
    $dumpvars(0, Lift8_Tb);    // Dump all variables in the module hierarchy

    clk = 1'b0;
    emergency_stop = 0;
    reset = 1;
    #10;
    reset = 0;
    req_floor = 1;
    #30;
    req_floor = 4;
    
    #10
    
    // Simulate elevator operation
    req_floor = 3; // Request floor 3
    #20;
    req_floor = 7; // Request floor 5
    #20;
    emergency_stop = 1; // Activate emergency stop
    #20;
    emergency_stop = 0; // Deactivate emergency stop
    #10;
    req_floor = 2; // Request floor 2
    #40;
    req_floor = 6; // Request floor 6
    #20;
    
    #20;
    req_floor = 1;
  end

  initial begin
  $display("Starting simulation...");
    $monitor("Time=%t,clk=%b,reset=%b,req_floor=%h,idle=%h,door=%h,Up=%h,Down=%h,current_floor=%h,max_request=%h,min_request=%h,requests=%h",
    $time, clk, reset, req_floor, idle, door, Up, Down, current_floor, max_request, min_request, requests);
  // Run the simulation for a sufficient duration
  #305; // Adjust the simulation time as needed
  $display("Simulation finished.");
  $finish;
end

// C
  always #5 clk = ~clk;
endmodule

waveform.vcd
$date
	Wed Oct  2 03:36:29 2024
$end
$version
	QuestaSim Version 2023.1
$end
$timescale
	1ns
$end

$scope module Lift8_Tb $end
$var reg 2 ! Down [1:0] $end
$var reg 2 " Up [1:0] $end
$var reg 1 # clk $end
$var reg 3 $ current_floor [2:0] $end
$var reg 2 % door [1:0] $end
$var reg 1 & emergency_stop $end
$var reg 2 ' idle [1:0] $end
$var reg 3 ( max_request [2:0] $end
$var reg 3 ) min_request [2:0] $end
$var reg 3 * req_floor [2:0] $end
$var reg 8 + requests [7:0] $end
$var reg 1 , reset $end

$scope module dut $end
$var wire 1 - clk $end
$var wire 1 . emergency_stop $end
$var wire 1 / reset $end
$var reg 2 0 Down [1:0] $end
$var reg 2 1 Up [1:0] $end
$var reg 3 2 current_floor [2:0] $end
$var reg 2 3 door [1:0] $end
$var reg 1 4 door_timer $end
$var reg 1 5 emergency_stopped $end
$var reg 1 6 flag $end
$var reg 2 7 idle [1:0] $end
$var reg 3 8 max_request [2:0] $end
$var reg 3 9 min_request [2:0] $end
$var reg 3 : req_floor [2:0] $end
$var reg 8 ; requests [7:0] $end
$upscope $end
$upscope $end
$enddefinitions $end
#0
$dumpvars
0.
1/
0-
bx !
bx "
0#
bx $
bx %
0&
bx '
bx (
bx )
bx *
bx +
1,
bx 0
bx 1
bx 2
bx 3
x4
x5
06
bx 7
bx 8
bx 9
bx :
bx ;
$end
#5
1#
1-
b0 2
b0 7
b0 3
b1 1
b0 0
b0 8
b111 9
b0 ;
05
b0 +
b111 )
b0 (
b0 !
b1 "
b0 %
b0 '
b0 $
#10
0,
b1 *
0#
b1 :
0/
0-
b10 ;
b1 8
b1 9
b1 )
b1 (
b10 +
#15
1#
1-
b1 2
b1 $
b1 7
b1 3
b0 ;
14
b0 +
b1 %
b1 '
#20
0#
0-
#25
1#
1-
b0 3
b0 %
#30
0#
0-
#35
1#
1-
#40
b100 *
0#
b100 :
0-
b10000 ;
b100 8
b100 (
b10000 +
#45
1#
1-
b10 2
b0 7
b0 '
b10 $
#50
b11 *
0#
b11 :
0-
b11000 ;
b11000 +
#55
1#
1-
b11 2
b11 $
b1 7
b1 3
b10000 ;
b10000 +
b1 %
b1 '
#60
0#
0-
#65
1#
1-
b0 3
b100 2
b0 7
b0 '
b100 $
b0 %
b1 7
b1 3
b0 ;
b0 +
b1 %
b1 '
#70
b111 *
0#
b111 :
0-
b10000000 ;
b111 8
b111 (
b10000000 +
#75
1#
1-
b0 3
b101 2
b0 7
b0 '
b101 $
b0 %
#80
0#
0-
#85
1#
1-
b110 2
b110 $
#90
1&
0#
1.
0-
#95
1#
1-
b1 7
16
15
b1 '
#100
0#
0-
#105
1#
1-
#110
0&
0#
0.
0-
#115
1#
1-
05
06
#120
b10 *
0#
b10 :
0-
b10000100 ;
b10 9
b10 )
b10000100 +
#125
1#
1-
b111 2
b0 7
b0 '
b111 $
b1 7
b1 3
b100 ;
b100 +
b1 %
b1 '
#130
0#
0-
#135
1#
1-
b0 3
b0 1
b1 0
b1 !
b0 "
b0 %
#140
0#
0-
#145
1#
1-
b110 2
b0 7
b0 '
b110 $
#150
0#
0-
#155
1#
1-
b101 2
b101 $
#160
b110 *
0#
b110 :
0-
b1000100 ;
b110 8
b110 (
b1000100 +
#165
1#
1-
b100 2
b100 $
#170
0#
0-
#175
1#
1-
b11 2
b11 $
#180
0#
0-
#185
1#
1-
b10 2
b10 $
b1 7
b1 3
b1000000 ;
b1000000 +
b1 %
b1 '
#190
0#
0-
#195
1#
1-
b0 3
b1 1
b0 0
b0 !
b1 "
b0 %
#200
b1 *
0#
b1 :
0-
b1000010 ;
b1 9
b1 )
b1000010 +
#205
1#
1-
b11 2
b0 7
b0 '
b11 $
#210
0#
0-
#215
1#
1-
b100 2
b100 $
#220
0#
0-
#225
1#
1-
b101 2
b101 $
#230
0#
0-
#235
1#
1-
b110 2
b110 $
b1 7
b1 3
b10 ;
b10 +
b1 %
b1 '
#240
0#
0-
#245
1#
1-
b0 3
b0 1
b1 0
b1 !
b0 "
b0 %
#250
0#
0-
#255
1#
1-
b101 2
b0 7
b0 '
b101 $
#260
0#
0-
#265
1#
1-
b100 2
b100 $
#270
0#
0-
#275
1#
1-
b11 2
b11 $
#280
0#
0-
#285
1#
1-
b10 2
b10 $
#290
0#
0-
#295
1#
1-
b1 2
b1 $
b1 7
b1 3
b0 ;
b0 +
b1 %
b1 '
